MLProto/Data.py
MLProto/Proto.py
MLProto/ProtoMake.py
MLProto/__init__.py
MLProto/Examples/__init__.py
MLProto/Examples/stock.py
MLProto/MLProto/Data.py
MLProto/MLProto/Proto.py
MLProto/MLProto/ProtoMake.py
MLProto/MLProto/__init__.py
MLProto-0.2.0.dist-info/LICENSE.txt
MLProto-0.2.0.dist-info/METADATA
MLProto-0.2.0.dist-info/WHEEL
MLProto-0.2.0.dist-info/entry_points.txt
MLProto-0.2.0.dist-info/top_level.txt
MLProto-0.2.0.dist-info/RECORD
