Metadata-Version: 2.1
Name: MLProto
Version: 0.2.0
Summary: Modular Neural Network Protyping for Stock Market Prediction
Home-page: https://github.com/CSLukeW/MLProto
Author: Luke Williams
Author-email: williams.luke.2001@gmail.com
License: UNKNOWN
Platform: UNKNOWN
Classifier: Programming Language :: Python :: 3
Classifier: License :: OSI Approved :: GNU Lesser General Public License v3 (LGPLv3)
Classifier: Operating System :: OS Independent
Classifier: Development Status :: 4 - Beta
Requires-Python: >=3.6
Requires-Dist: appdirs (==1.4.4)
Requires-Dist: audioread (==2.1.8)
Requires-Dist: cffi (==1.14.0)
Requires-Dist: cycler (==0.10.0)
Requires-Dist: decorator (==4.4.2)
Requires-Dist: distlib (==0.3.1)
Requires-Dist: filelock (==3.0.12)
Requires-Dist: joblib (==0.16.0)
Requires-Dist: kiwisolver (==1.2.0)
Requires-Dist: librosa (==0.7.2)
Requires-Dist: llvmlite (==0.33.0)
Requires-Dist: matplotlib (==3.2.2)
Requires-Dist: numba (==0.50.1)
Requires-Dist: numpy (==1.19.0)
Requires-Dist: pycparser (==2.20)
Requires-Dist: pyparsing (==2.4.7)
Requires-Dist: python-dateutil (==2.8.1)
Requires-Dist: resampy (==0.2.2)
Requires-Dist: scikit-learn (==0.23.1)
Requires-Dist: scipy (==1.5.1)
Requires-Dist: six (==1.15.0)
Requires-Dist: SoundFile (==0.10.3.post1)
Requires-Dist: tensorflow-estimator (==2.2.0)
Requires-Dist: termcolor (==1.1.0)
Requires-Dist: threadpoolctl (==2.1.0)
Requires-Dist: typing-extensions (==3.7.4.2)
Requires-Dist: urllib3 (==1.25.9)
Requires-Dist: virtualenv (==20.0.27)
Requires-Dist: werkzeug (==1.0.1)
Requires-Dist: wrapt (==1.12.1)
Requires-Dist: yarl (==1.4.2)
Requires-Dist: zipp (==3.1.0)
